pyramaterised/__init__.py
pyramaterised/circuit.py
pyramaterised/gates.py
pyramaterised/measure.py
pyramaterised/templates.py
pyramaterised-1.0.2.dist-info/LICENSE
pyramaterised-1.0.2.dist-info/METADATA
pyramaterised-1.0.2.dist-info/WHEEL
pyramaterised-1.0.2.dist-info/top_level.txt
pyramaterised-1.0.2.dist-info/RECORD
