Metadata-Version: 2.1
Name: pyramaterised
Version: 1.0.2
Summary: Library for building, simulating and measuring Parameterised Quantum Circuits (PQCs).
Author-email: Ronan Docherty <ronan.docherty18@imperial.ac.uk>
Project-URL: Homepage, https://github.com/rmdocherty/pyramaterised
Project-URL: Bug Tracker, https://github.com/rmdocherty/pyramaterised/issues
Classifier: Programming Language :: Python :: 3
Classifier: License :: OSI Approved :: MIT License
Classifier: Operating System :: OS Independent
Requires-Python: >=3.10
License-File: LICENSE
Requires-Dist: contourpy ==1.1.0
Requires-Dist: cycler ==0.11.0
Requires-Dist: flake8 ==6.1.0
Requires-Dist: fonttools ==4.42.1
Requires-Dist: kiwisolver ==1.4.4
Requires-Dist: matplotlib ==3.7.2
Requires-Dist: mccabe ==0.7.0
Requires-Dist: numpy ==1.25.2
Requires-Dist: packaging ==23.1
Requires-Dist: Pillow ==10.0.0
Requires-Dist: pycodestyle ==2.11.0
Requires-Dist: pyflakes ==3.1.0
Requires-Dist: pyparsing ==3.0.9
Requires-Dist: python-dateutil ==2.8.2
Requires-Dist: qutip ==4.7.2
Requires-Dist: scipy ==1.11.2
Requires-Dist: six ==1.16.0
